{
  "/Storedetail": "pages/Storedetail.html",
  "/_document": "pages/_document.js",
  "/_app": "pages/_app.js",
  "/about": "pages/about.html",
  "/Layout": "pages/Layout.html",
  "/_error": "pages/_error.js",
  "/api/racecar": "pages/api/racecar.js",
  "/all-stores": "pages/all-stores.html",
  "/contact": "pages/contact.html",
  "/": "pages/index.html",
  "/country/[slug]": "pages/country/[slug].html",
  "/pages/[slug]": "pages/pages/[slug].html",
  "/popular-coupons": "pages/popular-coupons.html",
  "/trending-coupon": "pages/trending-coupon.html",
  "/store/[slug]/[couponid]": "pages/store/[slug]/[couponid].html",
  "/coupon/[slug]": "pages/coupon/[slug].html",
  "/season/[slug]": "pages/season/[slug].html",
  "/category/[slug]": "pages/category/[slug].html",
  "/store/[slug]": "pages/store/[slug].html",
  "/category": "pages/category.js",
  "/404": "pages/404.html"
}